[
    {
        "dt": "2025-05-29",
        "code": "159226",
        "name": "\u4e2d\u8bc1A500\u589e\u5f3aETF",
        "share": "57,009.48"
    },
    {
        "dt": "2025-05-28",
        "code": "159226",
        "name": "\u4e2d\u8bc1A500\u589e\u5f3aETF",
        "share": "57,009.48"
    },
    {
        "dt": "2025-06-06",
        "code": "159226",
        "name": "\u4e2d\u8bc1A500\u589e\u5f3aETF",
        "share": "51,009.48"
    },
    {
        "dt": "2025-06-05",
        "code": "159226",
        "name": "\u4e2d\u8bc1A500\u589e\u5f3aETF",
        "share": "52,509.48"
    },
    {
        "dt": "2025-06-04",
        "code": "159226",
        "name": "\u4e2d\u8bc1A500\u589e\u5f3aETF",
        "share": "54,609.48"
    },
    {
        "dt": "2025-06-03",
        "code": "159226",
        "name": "\u4e2d\u8bc1A500\u589e\u5f3aETF",
        "share": "55,509.48"
    },
    {
        "dt": "2025-05-30",
        "code": "159226",
        "name": "\u4e2d\u8bc1A500\u589e\u5f3aETF",
        "share": "55,809.48"
    },
    {
        "dt": "2025-06-13",
        "code": "159226",
        "name": "\u4e2d\u8bc1A500\u589e\u5f3aETF",
        "share": "36,309.48"
    },
    {
        "dt": "2025-06-12",
        "code": "159226",
        "name": "\u4e2d\u8bc1A500\u589e\u5f3aETF",
        "share": "36,609.48"
    },
    {
        "dt": "2025-06-11",
        "code": "159226",
        "name": "\u4e2d\u8bc1A500\u589e\u5f3aETF",
        "share": "40,209.48"
    },
    {
        "dt": "2025-06-10",
        "code": "159226",
        "name": "\u4e2d\u8bc1A500\u589e\u5f3aETF",
        "share": "44,709.48"
    },
    {
        "dt": "2025-06-09",
        "code": "159226",
        "name": "\u4e2d\u8bc1A500\u589e\u5f3aETF",
        "share": "46,809.48"
    },
    {
        "dt": "2025-06-20",
        "code": "159226",
        "name": "\u4e2d\u8bc1A500\u589e\u5f3aETF",
        "share": "35,109.48"
    },
    {
        "dt": "2025-06-19",
        "code": "159226",
        "name": "\u4e2d\u8bc1A500\u589e\u5f3aETF",
        "share": "35,109.48"
    },
    {
        "dt": "2025-06-18",
        "code": "159226",
        "name": "\u4e2d\u8bc1A500\u589e\u5f3aETF",
        "share": "34,809.48"
    },
    {
        "dt": "2025-06-17",
        "code": "159226",
        "name": "\u4e2d\u8bc1A500\u589e\u5f3aETF",
        "share": "35,709.48"
    },
    {
        "dt": "2025-06-16",
        "code": "159226",
        "name": "\u4e2d\u8bc1A500\u589e\u5f3aETF",
        "share": "36,309.48"
    },
    {
        "dt": "2025-06-27",
        "code": "159226",
        "name": "\u4e2d\u8bc1A500\u589e\u5f3aETF",
        "share": "14,109.48"
    },
    {
        "dt": "2025-06-26",
        "code": "159226",
        "name": "\u4e2d\u8bc1A500\u589e\u5f3aETF",
        "share": "15,009.48"
    },
    {
        "dt": "2025-06-25",
        "code": "159226",
        "name": "\u4e2d\u8bc1A500\u589e\u5f3aETF",
        "share": "17,409.48"
    },
    {
        "dt": "2025-06-24",
        "code": "159226",
        "name": "\u4e2d\u8bc1A500\u589e\u5f3aETF",
        "share": "25,809.48"
    },
    {
        "dt": "2025-06-23",
        "code": "159226",
        "name": "\u4e2d\u8bc1A500\u589e\u5f3aETF",
        "share": "34,809.48"
    },
    {
        "dt": "2025-07-04",
        "code": "159226",
        "name": "\u4e2d\u8bc1A500\u589e\u5f3aETF",
        "share": "9,909.48"
    },
    {
        "dt": "2025-07-03",
        "code": "159226",
        "name": "\u4e2d\u8bc1A500\u589e\u5f3aETF",
        "share": "11,409.48"
    },
    {
        "dt": "2025-07-02",
        "code": "159226",
        "name": "\u4e2d\u8bc1A500\u589e\u5f3aETF",
        "share": "12,609.48"
    },
    {
        "dt": "2025-07-01",
        "code": "159226",
        "name": "\u4e2d\u8bc1A500\u589e\u5f3aETF",
        "share": "12,909.48"
    },
    {
        "dt": "2025-06-30",
        "code": "159226",
        "name": "\u4e2d\u8bc1A500\u589e\u5f3aETF",
        "share": "13,509.48"
    },
    {
        "dt": "2025-07-11",
        "code": "159226",
        "name": "\u4e2d\u8bc1A500\u589e\u5f3aETF",
        "share": "7,209.48"
    },
    {
        "dt": "2025-07-10",
        "code": "159226",
        "name": "\u4e2d\u8bc1A500\u589e\u5f3aETF",
        "share": "7,809.48"
    },
    {
        "dt": "2025-07-09",
        "code": "159226",
        "name": "\u4e2d\u8bc1A500\u589e\u5f3aETF",
        "share": "8,109.48"
    },
    {
        "dt": "2025-07-08",
        "code": "159226",
        "name": "\u4e2d\u8bc1A500\u589e\u5f3aETF",
        "share": "8,709.48"
    },
    {
        "dt": "2025-07-07",
        "code": "159226",
        "name": "\u4e2d\u8bc1A500\u589e\u5f3aETF",
        "share": "9,609.48"
    },
    {
        "dt": "2025-07-14",
        "code": "159226",
        "name": "\u4e2d\u8bc1A500\u589e\u5f3aETF",
        "share": "7,209.48"
    },
    {
        "dt": "2025-07-15",
        "code": "159226",
        "name": "\u4e2d\u8bc1A500\u589e\u5f3aETF",
        "share": "6,909.48"
    }
]